[
  {
    "name": "prod1",
    "id": 1,
    "price": 10.99,
    "image": "https://www.w3schools.com/images/picture.jpg",
    "description": "Lorem ipsum dolor sit amet, consectetur adipiscing sdas."
  },
  {
    "name": "prod2",
    "id": 2,
    "price": 19.99,
    "image": "https://raw.githubusercontent.com/sudofaizan/Ecom-Sample/main/Product_images/product2.jpg",
    "description": "Sed do eiusmod tempor incididunt ut labore et dolore magna aliqua."
  },
  {
    "name": "prod3",
    "id": 3,
    "price": 19.99,
    "image": "https://raw.githubusercontent.com/sudofaizan/Ecom-Sample/main/Product_images/product2.jpg",
    "description": "Sed do eiusmod tempor incididunt ut labore et dolore magna aliqua."
  },
  {
    "name": "prod4",
    "id": 4,
    "price": 19.99,
    "image": "https://raw.githubusercontent.com/sudofaizan/Ecom-Sample/main/Product_images/product2.jpg",
    "description": "Sed do eiusmod tempor incididunt ut labore et dolore magna aliqua."
  }
]
